agentos_db/__init__.py
agentos_db/database.py
agentos_db/models/__init__.py
agentos_db/models/base.py
agentos_db/models/public.py
agentos_db-0.1.2.dist-info/METADATA
agentos_db-0.1.2.dist-info/WHEEL
agentos_db-0.1.2.dist-info/top_level.txt
agentos_db-0.1.2.dist-info/RECORD
