Metadata-Version: 2.2
Name: agentos-db
Version: 0.1.2
Summary: The shared database for AgentOS
Author: AgentOS
Requires-Dist: sqlalchemy>=2.0.0
Requires-Dist: python-dotenv>=1.0.0
Requires-Dist: psycopg2-binary>=2.9.0
Dynamic: author
Dynamic: requires-dist
Dynamic: summary
